verilog/definitions.v
// constants
`define OFF 1'b0
`define ON  1'b1

// clock specs (tb)
`define SWITCH 5
`define DELAY  `SWITCH * 2

// bit-width / word length
`define BIT_DATA 16
`define BIT_INST 16
`define BIT_OP   4     

// array sizes
`define SZB_INS  4
`define SZB_REG  4
`define SZB_RAM  8

// opcodes
`define LOAD   4'b0000
`define STORE  4'b0001
`define MOVE   4'b0010
`define JUMP   4'b0011
`define INV    4'b0100
`define AND    4'b0101
`define OR     4'b0110
`define XOR    4'b0111
`define XNOR   4'b1000
`define COM    4'b1001
`define SHR    4'b1010
`define SHL    4'b1011
`define ADD    4'b1100
`define SUB    4'b1101
`define MUL    4'b1110
`define DIV    4'b1111

// interrupts
`define LD_REG  4'b0000
`define LD_RAM  4'b0001
`define LD_INS  4'b0010
`define OUT_REG 4'b0011
`define OUT_RAM 4'b0100

verilog/regfile.v
`include "./definitions.v"

module regfile
#(
    parameter BIT = 8,
    parameter SZB = 4
 )
(
    input clock, reset, rd_we, en_mv,

    input [SZB - 1 : 0] addr_rs0, addr_rs1, addr_rd,

    input [`BIT_DATA - 1 : 0] rd,

    output [`BIT_DATA - 1 : 0] rs0, rs1
);

    localparam SZA = 2 ** SZB;

    reg [`BIT_DATA - 1 : 0] regf [0 : SZA - 1];

    integer ri;

    always @(posedge clock or posedge reset) begin

        if (reset) begin

            for (ri = 0; ri < SZA; ri = ri + 1) regf [ri] <= {`BIT_DATA{`OFF}};
            
        end

        else if (rd_we) regf [addr_rd] <= rd;

        else if (en_mv) regf [addr_rd] <= regf [addr_rs0];

        else regf [0] <= regf [0];
        
    end

    assign rs0 = regf [addr_rs0];
    assign rs1 = regf [addr_rs1];
    
endmodule

verilog/tb_regfile.v
`include "./definitions.v"
`include "./regfile.v"

// `timescale <unit> / <precision>
`timescale 1ns/100ps

module tb_regfile ();
    
    // output waveform
    initial begin

        $dumpfile("testbench/regfile.vcd");
        $dumpvars;
        
    end

    // test parameters
    integer i, ia, ib;

    localparam SZA = 2 ** `SZB_REG;
    localparam UPP = 2 ** `BIT_DATA;

    // test io
    reg clock, reset, rd_we, en_mv, write_inst;

    reg [`SZB_REG  - 1 : 0] addr_rs0, addr_rs1, addr_rd;
    reg [`SZB_INS  - 1 : 0] addr_inst;
    reg [`BIT_DATA - 1 : 0] rd, d;

    wire [`BIT_DATA - 1 : 0] rs0, rs1, q;

    // test verification


    // test module
    regfile #(.BIT (`BIT_DATA),
              .SZB (`SZB_REG))  dreg
    (
        .clock (clock),
        .reset (reset),
        .rd_we (rd_we),
        .en_mv (en_mv),

        .addr_rs0 (addr_rs0),
        .addr_rs1 (addr_rs1),
        .addr_rd  (addr_rd),

        .rd  (rd),
        .rs0 (rs0),
        .rs1 (rs1)
    );

    regfile #(.BIT (`BIT_DATA),
              .SZB (`SZB_REG))  ireg
    (
        .clock (clock),
        .reset (reset),
        .rd_we (write_inst),
        .en_mv (`OFF),

        .addr_rs0 (addr_inst),
        .addr_rs1 ({`SZB_REG{`OFF}}),
        .addr_rd  (addr_inst),

        .rd  (d),
        .rs0 (q)
    );

    // clock generator
    initial           clock <= `OFF;
    always #(`SWITCH) clock <= ~clock;

    // test sequences
    initial begin

        // initialise
        reset <= `ON;

        rd_we      <= `OFF;
        en_mv      <= `OFF;

        addr_rs0   <= {`SZB_REG{`OFF}};
        addr_rs1   <= {`SZB_REG{`OFF}};
        addr_rd    <= {`SZB_REG{`OFF}};
        addr_inst  <= {`SZB_INS{`OFF}};
        
        rd <= {`BIT_DATA{`OFF}};

        #(`DELAY)

        reset <= `OFF;

        rd_we <= `ON;

        #1

        // test: store data
        for (i = 0; i < SZA; i = i + 1) begin

            #(`DELAY)

            addr_rs0  <= i;
            addr_rs1  <= i + 1;
            addr_rd   <= i;
            addr_inst <= i;

            rd <= $random % UPP;
            
        end

        ia <= $random % SZA;
        ib <= $random % SZA;

        #(`DELAY)

        // test: move data
        rd_we <= `OFF;
        en_mv <= `ON;

        addr_rs0 <= ia;
        addr_rs1 <= ib;
        addr_rd  <= ib;

        #(`DELAY)

        en_mv <= `OFF;

        #(`DELAY)

        $finish();
        
    end

    initial begin

        // initialise
        write_inst <= `OFF;        
        d          <= {`BIT_DATA{`OFF}};
        write_inst <= `OFF;

        #(`DELAY)

        // test: store instructions
        write_inst <= `ON;

        #1

        // 0
        d <= {`LOAD, 4'd0, 8'd0};

        #(`DELAY)

        // 1
        d <= {`STORE, 8'd1, 4'd1};

        #(`DELAY)

        // 2
        d <= {`MOVE, 4'd0, 4'd2, 4'b0};

        #(`DELAY)

        // 3
        d <= {`JUMP, 4'd2, 8'b0};

        #(`DELAY)

        // 4
        d <= {`INV, 4'd3, 4'd1, 4'b0};

        #(`DELAY)

        // 5
        d <= {`AND, 4'd4, 4'd3, 4'd2};

        #(`DELAY)

        // 6
        d <= {`OR, 4'd5, 4'd3, 4'd2};

        #(`DELAY)

        // 7
        d <= {`XOR, 4'd6, 4'd3, 4'd2};

        #(`DELAY)

        // 8
        d <= {`XNOR, 4'd7, 4'd3, 4'd2};

        #(`DELAY)

        // 9
        d <= {`COM, 4'd8, 4'd3, 4'd2};

        #(`DELAY)

        // 10
        d <= {`SHR, 4'd9, 4'd3, 4'd2};

        #(`DELAY)

        // 11
        d <= {`SHL, 4'd10, 4'd3, 4'd2};

        #(`DELAY)

        // 12
        d <= {`ADD, 4'd11, 4'd3, 4'd2};

        #(`DELAY)

        // 13
        d <= {`SUB, 4'd12, 4'd3, 4'd2};

        #(`DELAY)

        // 14
        d <= {`MUL, 4'd13, 4'd3, 4'd2};

        #(`DELAY)

        // 15
        d <= {`DIV, 4'd14, 4'd3, 4'd2};

        #(`DELAY)

        write_inst <= `OFF;
        
    end
    
endmodule

verilog/testbench/regfile.vcd
$date
	Thu May 12 19:17:56 2022
$end
$version
	Icarus Verilog
$end
$timescale
	100ps
$end
$scope module tb_regfile $end
$var wire 16 ! rs1 [15:0] $end
$var wire 16 " rs0 [15:0] $end
$var wire 16 # q [15:0] $end
$var reg 4 $ addr_inst [3:0] $end
$var reg 4 % addr_rd [3:0] $end
$var reg 4 & addr_rs0 [3:0] $end
$var reg 4 ' addr_rs1 [3:0] $end
$var reg 1 ( clock $end
$var reg 16 ) d [15:0] $end
$var reg 1 * en_mv $end
$var reg 16 + rd [15:0] $end
$var reg 1 , rd_we $end
$var reg 1 - reset $end
$var reg 1 . write_inst $end
$var integer 32 / i [31:0] $end
$var integer 32 0 ia [31:0] $end
$var integer 32 1 ib [31:0] $end
$scope module dreg $end
$var wire 4 2 addr_rd [3:0] $end
$var wire 4 3 addr_rs0 [3:0] $end
$var wire 4 4 addr_rs1 [3:0] $end
$var wire 1 ( clock $end
$var wire 1 * en_mv $end
$var wire 16 5 rd [15:0] $end
$var wire 1 , rd_we $end
$var wire 1 - reset $end
$var wire 16 6 rs0 [15:0] $end
$var wire 16 7 rs1 [15:0] $end
$var integer 32 8 ri [31:0] $end
$upscope $end
$scope module ireg $end
$var wire 4 9 addr_rd [3:0] $end
$var wire 4 : addr_rs0 [3:0] $end
$var wire 4 ; addr_rs1 [3:0] $end
$var wire 1 ( clock $end
$var wire 1 < en_mv $end
$var wire 16 = rd [15:0] $end
$var wire 1 . rd_we $end
$var wire 1 - reset $end
$var wire 16 > rs0 [15:0] $end
$var wire 16 ? rs1 [15:0] $end
$var integer 32 @ ri [31:0] $end
$upscope $end
$upscope $end
$enddefinitions $end
#0
$dumpvars
b10000 @
b0 ?
b0 >
b0 =
0<
b0 ;
b0 :
b0 9
b10000 8
b0 7
b0 6
b0 5
b0 4
b0 3
b0 2
bx 1
bx 0
bx /
0.
1-
0,
b0 +
0*
b0 )
0(
b0 '
b0 &
b0 %
b0 $
b0 #
b0 "
b0 !
$end
#50
b10000 @
b10000 8
1(
#100
0(
1.
1,
0-
#110
b0 /
#150
1(
#200
0(
#210
b1000000010001 )
b1000000010001 =
b11010100100100 +
b11010100100100 5
b1 '
b1 4
b1 /
#250
b1000000010001 #
b1000000010001 >
b1000000010001 ?
b11010100100100 "
b11010100100100 6
1(
#300
0(
#310
b10000000100000 )
b10000000100000 =
b101111010000001 +
b101111010000001 5
b0 #
b0 >
b1 $
b1 9
b1 :
b1 %
b1 2
b10 '
b10 4
b0 "
b0 6
b1 &
b1 3
b10 /
#350
b101111010000001 "
b101111010000001 6
b10000000100000 #
b10000000100000 >
1(
#400
0(
#410
b11001000000000 )
b11001000000000 =
b1101011000001001 +
b1101011000001001 5
b0 #
b0 >
b10 $
b10 9
b10 :
b10 %
b10 2
b11 '
b11 4
b0 "
b0 6
b10 &
b10 3
b11 /
#450
b11001000000000 #
b11001000000000 >
b1101011000001001 "
b1101011000001001 6
1(
#500
0(
#510
b100001100010000 )
b100001100010000 =
b101011001100011 +
b101011001100011 5
b0 #
b0 >
b11 $
b11 9
b11 :
b11 %
b11 2
b100 '
b100 4
b0 "
b0 6
b11 &
b11 3
b100 /
#550
b101011001100011 "
b101011001100011 6
b100001100010000 #
b100001100010000 >
1(
#600
0(
#610
b101010000110010 )
b101010000110010 =
b111101100001101 +
b111101100001101 5
b0 #
b0 >
b100 $
b100 9
b100 :
b100 %
b100 2
b101 '
b101 4
b0 "
b0 6
b100 &
b100 3
b101 /
#650
b101010000110010 #
b101010000110010 >
b111101100001101 "
b111101100001101 6
1(
#700
0(
#710
b110010100110010 )
b110010100110010 =
b1001100110001101 +
b1001100110001101 5
b0 #
b0 >
b101 $
b101 9
b101 :
b101 %
b101 2
b110 '
b110 4
b0 "
b0 6
b101 &
b101 3
b110 /
#750
b1001100110001101 "
b1001100110001101 6
b110010100110010 #
b110010100110010 >
1(
#800
0(
#810
b111011000110010 )
b111011000110010 =
b1000010001100101 +
b1000010001100101 5
b0 #
b0 >
b110 $
b110 9
b110 :
b110 %
b110 2
b111 '
b111 4
b0 "
b0 6
b110 &
b110 3
b111 /
#850
b111011000110010 #
b111011000110010 >
b1000010001100101 "
b1000010001100101 6
1(
#900
0(
#910
b1000011100110010 )
b1000011100110010 =
b101001000010010 +
b101001000010010 5
b0 #
b0 >
b111 $
b111 9
b111 :
b111 %
b111 2
b1000 '
b1000 4
b0 "
b0 6
b111 &
b111 3
b1000 /
#950
b101001000010010 "
b101001000010010 6
b1000011100110010 #
b1000011100110010 >
1(
#1000
0(
#1010
b1001100000110010 )
b1001100000110010 =
b1110001100000001 +
b1110001100000001 5
b0 #
b0 >
b1000 $
b1000 9
b1000 :
b1000 %
b1000 2
b1001 '
b1001 4
b0 "
b0 6
b1000 &
b1000 3
b1001 /
#1050
b1001100000110010 #
b1001100000110010 >
b1110001100000001 "
b1110001100000001 6
1(
#1100
0(
#1110
b1010100100110010 )
b1010100100110010 =
b1100110100001101 +
b1100110100001101 5
b0 #
b0 >
b1001 $
b1001 9
b1001 :
b1001 %
b1001 2
b1010 '
b1010 4
b0 "
b0 6
b1001 &
b1001 3
b1010 /
#1150
b1100110100001101 "
b1100110100001101 6
b1010100100110010 #
b1010100100110010 >
1(
#1200
0(
#1210
b1011101000110010 )
b1011101000110010 =
b1111000101110110 +
b1111000101110110 5
b0 #
b0 >
b1010 $
b1010 9
b1010 :
b1010 %
b1010 2
b1011 '
b1011 4
b0 "
b0 6
b1010 &
b1010 3
b1011 /
#1250
b1011101000110010 #
b1011101000110010 >
b1111000101110110 "
b1111000101110110 6
1(
#1300
0(
#1310
b1100101100110010 )
b1100101100110010 =
b1100110100111101 +
b1100110100111101 5
b0 #
b0 >
b1011 $
b1011 9
b1011 :
b1011 %
b1011 2
b1100 '
b1100 4
b0 "
b0 6
b1011 &
b1011 3
b1100 /
#1350
b1100110100111101 "
b1100110100111101 6
b1100101100110010 #
b1100101100110010 >
1(
#1400
0(
#1410
b1101110000110010 )
b1101110000110010 =
b101011111101101 +
b101011111101101 5
b0 #
b0 >
b1100 $
b1100 9
b1100 :
b1100 %
b1100 2
b1101 '
b1101 4
b0 "
b0 6
b1100 &
b1100 3
b1101 /
#1450
b1101110000110010 #
b1101110000110010 >
b101011111101101 "
b101011111101101 6
1(
#1500
0(
#1510
b1110110100110010 )
b1110110100110010 =
b1111011110001100 +
b1111011110001100 5
b0 #
b0 >
b1101 $
b1101 9
b1101 :
b1101 %
b1101 2
b1110 '
b1110 4
b0 "
b0 6
b1101 &
b1101 3
b1110 /
#1550
b1111011110001100 "
b1111011110001100 6
b1110110100110010 #
b1110110100110010 >
1(
#1600
0(
#1610
b1111111000110010 )
b1111111000110010 =
b1110100111111001 +
b1110100111111001 5
b0 #
b0 >
b1110 $
b1110 9
b1110 :
b1110 %
b1110 2
b1111 '
b1111 4
b0 "
b0 6
b1110 &
b1110 3
b1111 /
#1650
b1111111000110010 #
b1111111000110010 >
b1110100111111001 "
b1110100111111001 6
1(
#1700
0(
#1710
0.
b11111111111111111111111111111010 1
b11111111111111111111111111110101 0
b10010011000110 +
b10010011000110 5
b0 #
b0 >
b1111 $
b1111 9
b1111 :
b1111 %
b1111 2
b11010100100100 !
b11010100100100 7
b0 '
b0 4
b0 "
b0 6
b1111 &
b1111 3
b10000 /
#1750
b10010011000110 "
b10010011000110 6
1(
#1800
0(
#1810
b1010 %
b1010 2
b1111000101110110 !
b1111000101110110 7
b1010 '
b1010 4
b1001100110001101 "
b1001100110001101 6
b101 &
b101 3
1*
0,
#1850
b1001100110001101 !
b1001100110001101 7
1(
#1900
0(
#1910
0*
